datarize/main.py
datarize-0.0.1.dist-info/LICENSE
datarize-0.0.1.dist-info/METADATA
datarize-0.0.1.dist-info/WHEEL
datarize-0.0.1.dist-info/RECORD
